{"missionId": "178", "missionName": "Gefahrgut-LKW verunglückt", "requirements": [{"requirement": "gkw", "qty": "1"}, {"requirement": "löschfahrzeuge", "qty": "3"}, {"requirement": "elw 1", "qty": "1"}, {"requirement": "elw 2", "qty": "1"}, {"requirement": "rüstwagen", "qty": "1"}, {"requirement": "gw-mess", "qty": "1"}, {"requirement": "dekon-p", "qty": "1"}, {"requirement": "gw-gefahrgut", "qty": "1"}, {"requirement": "streifenwagen", "qty": "2"}, {"requirement": "maximale patientenanzahl", "qty": "1"}], "credits": "2900"}