{"missionId": "545-0", "missionName": "Brand bei Holzverarbeiter", "requirements": [{"requirement": "löschfahrzeuge", "qty": "14"}, {"requirement": "drehleitern", "qty": "3"}, {"requirement": "elw 1", "qty": "2"}, {"requirement": "elw 2", "qty": "1"}, {"requirement": "gw-a", "qty": "1"}, {"requirement": "gw l 2 wasser", "qty": "1"}, {"requirement": "rüstwagen", "qty": "2"}, {"requirement": "gw-mess", "qty": "1"}, {"requirement": "streifenwagen", "qty": "4"}, {"requirement": "gkw", "qty": "1"}, {"requirement": "mzkw", "qty": "1"}, {"requirement": "mtw-tz", "qty": "1"}, {"requirement": "funkstreifenwagen (dienstgruppenleitung)", "qty": "1"}, {"requirement": "radlader (brmg r)", "qty": "1"}, {"requirement": "rtw, naw", "qty": "6"}, {"requirement": "nef", "qty": "4"}, {"requirement": "lna", "qty": "1"}], "credits": "9650"}