{"missionId": "689", "missionName": "Straßenblockade", "requirements": [{"requirement": "streifenwagen", "qty": "8"}, {"requirement": "dhufükw", "qty": "2"}, {"requirement": "grukw", "qty": "18"}, {"requirement": "lebefkw", "qty": "7"}, {"requirement": "gefkw", "qty": "2"}, {"requirement": "fükw", "qty": "2"}, {"requirement": "polizeihubschrauber", "qty": "1"}, {"requirement": "wasserwerfer", "qty": "3"}, {"requirement": "zivilstreifenwagen", "qty": "2"}, {"requirement": "funkstreifenwagen (dienstgruppenleitung)", "qty": "1"}, {"requirement": "maximale patientenanzahl", "qty": "35"}], "credits": "14500"}