{"missionId": "274", "missionName": "Klein vliegtuig neergestort", "requirements": [{"requirement": "tankautospuiten", "qty": "2"}, {"requirement": "hulpverleningsvoertuigen", "qty": "1"}, {"requirement": "ovd-b's", "qty": "1"}, {"requirement": "hovd's", "qty": "1"}, {"requirement": "commandowagen", "qty": "1"}, {"requirement": "noodhulpeenheden", "qty": "2"}, {"requirement": "officiers van dienst politie", "qty": "1"}, {"requirement": "maximale patiënten aantal", "qty": "4"}, {"requirement": "ovd-geneeskunde", "qty": "1"}, {"requirement": "crashtender", "qty": "1"}], "credits": "3000"}